popsummary/__init__.py
popsummary/popresult.py
popsummary/utils.py
popsummary-0.1.0.dist-info/licenses/LICENSE
popsummary-0.1.0.dist-info/METADATA
popsummary-0.1.0.dist-info/WHEEL
popsummary-0.1.0.dist-info/top_level.txt
popsummary-0.1.0.dist-info/RECORD
