Metadata-Version: 2.4
Name: popsummary
Version: 0.1.0
Summary: A Python API for interfacing with standardized LIGO-Virgo-KAGRA Rates and Populations results
Home-page: https://git.ligo.org/RatesAndPopulations/popsummary
Author: Christian Adamcewicz, Zoheyr Doctor
Author-email: christian.adamcewicz@ligo.org
Requires-Python: >=3.9
License-File: LICENSE
Requires-Dist: h5py
Requires-Dist: numpy
Provides-Extra: test
Requires-Dist: scipy; extra == "test"
Requires-Dist: astropy; extra == "test"
Requires-Dist: nbconvert; extra == "test"
Requires-Dist: nbstrip; extra == "test"
Requires-Dist: ipykernel; extra == "test"
Dynamic: author
Dynamic: author-email
Dynamic: description
Dynamic: description-content-type
Dynamic: home-page
Dynamic: license-file
Dynamic: provides-extra
Dynamic: requires-dist
Dynamic: requires-python
Dynamic: summary
